maic/__init__.py
maic/__init__.pyi
maic/constants.py
maic/constants.pyi
maic/cross_validation.py
maic/cross_validation.pyi
maic/entity.py
maic/entity.pyi
maic/entitylist.py
maic/entitylist.pyi
maic/errors.py
maic/errors.pyi
maic/py.typed
maic/cli/__init__.py
maic/cli/options.py
maic/cli/options.pyi
maic/io/__init__.py
maic/io/__init__.pyi
maic/io/cv_dumper.py
maic/io/cv_dumper.pyi
maic/io/cv_plotter.py
maic/io/cv_plotter.pyi
maic/io/genescores_dumper.py
maic/io/genescores_dumper.pyi
maic/models/__init__.py
maic/models/__init__.pyi
pymaic-0.2.dist-info/LICENSE
pymaic-0.2.dist-info/METADATA
pymaic-0.2.dist-info/WHEEL
pymaic-0.2.dist-info/entry_points.txt
pymaic-0.2.dist-info/top_level.txt
pymaic-0.2.dist-info/RECORD
