Metadata-Version: 2.1
Name: pymaic
Version: 0.2
Author-email: J Kenneth Baillie <j.k.baillie@ed.ac.uk>, Andy Law <andy.law@roslin.ed.ac.uk>, Bo Wang <bo.wang@roslin.ed.ac.uk>, David Farr <contact@baillielab.net>
Maintainer-email: Jim McGrath <jim.mcgrath@ed.ac.uk>
License: MIT License
Project-URL: homepage, https://baillielab.net/maic
Project-URL: repository, https://github.com/baillielab/maic
Project-URL: pacckage_repo, https://github.com/baillielab/maic/tree/packaging
Requires-Python: >=3.6
License-File: LICENSE
Requires-Dist: mock
Requires-Dist: coverage
Requires-Dist: numpy
Requires-Dist: scipy
Requires-Dist: scikit-learn
Requires-Dist: matplotlib
Requires-Dist: oyaml
